file_renamer/__init__.py
file_renamer/__main__.py
file_renamer/form.ui
file_renamer/gui.py
file_renamer/icons.qrc
file_renamer/rc_icons.py
file_renamer/rename.py
file_renamer/ui_form.py
file_renamer/version.py
file_renamer/widget.py
file_renamer/cli/__init__.py
file_renamer/html/imagine.qrc
file_renamer/html/rbe.qrc
file_renamer/html/rc_imagine.py
file_renamer/html/rc_rbe.py
file_renamer/html/rc_ui.py
file_renamer/html/ui.qrc
file_renamer/html/css/bootstrap.min.css
file_renamer/html/js/bootstrap.bundle.min.js
file_renamer/html/media/John-Lennon-Imagine-1971.mp4
file_renamer/html/media/The-Lost-Children-Of-Babylon-The-Venus-Project-2010.mp4
file_renamer/html/media/lyrics/John-Lennon-Imagine-1971.ass
file_renamer/html/media/lyrics/The-Lost-Children-Of-Babylon-The-Venus-Project-2010.ass
file_renamer/icons/file-renamer-1024x1024.icns
file_renamer/icons/file-renamer-1024x1024.png
file_renamer/icons/file-renamer-32x32.ico
file_renamer/icons/file-renamer-32x32.png
file_renamer/icons/file-renamer-512x512.icns
file_renamer/icons/file-renamer-512x512.ico
file_renamer/icons/file-renamer-512x512.png
file_renamer/lib/case.py
file_renamer/lib/exceptions.py
file_renamer/lib/files.py
file_renamer/lib/html.py
file_renamer/themes/theme.py
file_renamer/themes/dark/dark_linux.py
file_renamer/themes/dark/dark_windows.py
file_renamer/themes/light/light_linux.py
file_renamer/themes/light/light_windows.py
file_renamer-1.1.4.dist-info/METADATA
file_renamer-1.1.4.dist-info/WHEEL
file_renamer-1.1.4.dist-info/entry_points.txt
file_renamer-1.1.4.dist-info/licenses/LICENSE
file_renamer-1.1.4.dist-info/RECORD
