Metadata-Version: 2.3
Name: file-renamer
Version: 1.1.4
Summary: Rename files using a GUI desktop app for Linux & Windows. macOS not yet tested.
Project-URL: Homepage, https://github.com/mcarlos101/file-renamer
Project-URL: Repository, https://github.com/mcarlos101/file-renamer.git
Author: Carlos
License-File: LICENSE
Keywords: app,batch-rename-files,fedora,gui,linux-desktop,macos-desktop,pyside6,qcreator,qt,rename,rename-files,renamer,ubuntu,windows-desktop
Classifier: License :: OSI Approved :: GNU General Public License v3 or later (GPLv3+)
Classifier: Operating System :: OS Independent
Classifier: Programming Language :: Python :: 3
Requires-Python: >=3.12
Requires-Dist: pyside6-addons==6.7.0
Requires-Dist: pyside6-essentials==6.7.0
Requires-Dist: pyside6==6.7.0
Requires-Dist: shiboken6==6.7.0
Requires-Dist: unidecode==1.3.8
